pygdl/__init__.py
pygdl/__main__.py
pygdl-1.0.5.dist-info/LICENSE
pygdl-1.0.5.dist-info/METADATA
pygdl-1.0.5.dist-info/WHEEL
pygdl-1.0.5.dist-info/entry_points.txt
pygdl-1.0.5.dist-info/top_level.txt
pygdl-1.0.5.dist-info/RECORD
