Metadata-Version: 2.2
Name: pygdl
Version: 1.0.5
Summary: A python based downloader for github release files.
Author-email: Soumyo Deep Gupta <deep.main.ac@gmail.com>
Maintainer-email: Soumyo Deep Gupta <deep.main.ac@gmail.com>
License: MIT License
Classifier: Development Status :: 4 - Beta
Classifier: Programming Language :: Python :: 3.13
Classifier: License :: OSI Approved :: MIT License
Classifier: Operating System :: MacOS :: MacOS X
Classifier: Operating System :: POSIX :: Linux
Classifier: Operating System :: Microsoft :: Windows
Classifier: Programming Language :: Python :: 3
Classifier: Programming Language :: Python :: 3 :: Only
Requires-Python: >=3.8
License-File: LICENSE
Requires-Dist: tqdm
Requires-Dist: argpi
Requires-Dist: requests
